<?xml version="1.0" encoding="utf-8"?>
<openerp>
    <data>

      <record model="ir.ui.view" id="account_asset_remove_form_simply">
        <field name="name">account.asset.remove.form.simply</field>
        <field name="model">account.asset.remove</field>
        <field name="inherit_id" ref="account_asset_management.account_asset_remove_form"/>
        <field name="arch" type="xml">
            <button name="remove" position="after">
                <button string="Set to removed without generating Removal entries" name="set_to_removed" type="object" />
            </button>
        </field>
      </record>

    </data>
</openerp>